smurf/__init__.py
smurf/docopt_cli.py
smurf/metadata.py
smurf-2019.6.3.dist-info/METADATA
smurf-2019.6.3.dist-info/WHEEL
smurf-2019.6.3.dist-info/entry_points.txt
smurf-2019.6.3.dist-info/top_level.txt
smurf-2019.6.3.dist-info/RECORD
