Metadata-Version: 2.1
Name: smurf
Version: 2019.6.3
Summary: string morping, for smurfing from a string to another
Home-page: https://github.com/e7dal/smurf
Author: Erdal Yildiz
Author-email: erdalyildiz1974@gmail.com
Maintainer: Erdal Yildiz
Maintainer-email: erdalyildiz1974@gmail.com
License: GPL-3.0
Keywords: string morphing,cli,smurfing
Platform: UNKNOWN
Classifier: Development Status :: 4 - Beta
Classifier: Intended Audience :: Developers
Classifier: Operating System :: POSIX :: Linux
Classifier: Environment :: Console
Classifier: Programming Language :: Python :: 3.6
Requires-Dist: docopt
